{"Name":"BillTypeEdit","Type":"View","EventActions":[{"Name":"BackToLast","Type":"Page/ToPage","PageUrl":"/PurchaseSaleManage/BillTypeList"},{"Name":"SaveEntityData","Type":"EntityEdit/SaveEntityData","EditView":"BillTypeEdit2"},{"Name":"GetEntityData","Type":"EntityEdit/GetEntityData","EditView":"BillTypeEdit2"}],"Properties":[{"Name":"BillTypeEdit2","Type":"RowsColsView","Entity":{"Name":"BillType","PrimaryKey":"Id"},"IsForm":true,"EventActionName":"GetEntityData","IsClear":true,"SaveEntityDataActionType":2201,"GetEntityDataActionType":2200,"Properties":[{"Name":"IncomePayment","Label":"收支","Type":"Radio","DataSource":[{"Value":2,"Text":"支出"},{"Value":1,"Text":"收入"}],"X":1,"Y":1,"IsButton":true,"DefaultValue":2,"ButtonWidth":"50%","IsFormItem":true,"ColSpan":24,"IsLoadValue":true,"LabelCol":8,"WrapperCol":8,"Style":{"width":"100%"},"IsEdit":true,"RowId":"2600000001","ColId":"2600000002","Id":"2600000003","IsNullable":true},{"Name":"Name","Label":"名称","Type":"TextBox","ControlType":"","PlaceHolder":"请输入名称","X":2,"Y":1,"MaxLength":50,"IsFormItem":true,"ColSpan":24,"LabelCol":8,"WrapperCol":8,"IsNullable":false,"IsEdit":true,"RowId":"2600000004","ColId":"2600000005","Id":"2600000006"},{"Name":"Remark","Label":"备注","Type":"TextBox","ControlType":"TextArea","X":3,"Y":1,"IsFormItem":true,"IsNullable":true,"IsEdit":true,"ColSpan":24,"Rows":3,"LabelCol":8,"WrapperCol":8,"RowId":"2600000007","ColId":"2600000008","Id":"2600000009"},{"Name":"ButtonView","Type":"View","ClassName":"DivCenterButton","IsDiv":true,"IsFormItem":true,"ColSpan":24,"X":6,"Y":1,"Properties":[{"Name":"LeftSpace1","Type":"WhiteSpace","ClassName":"ant-col ant-col-8 ant-form-item-label","X":1,"Y":1,"RowId":"2500000001","ColId":"2500000002","Id":"2500000003","IsNullable":true},{"Name":"SaveEntityData","Text":"保存","Type":"Button","ButtonType":"primary","X":2,"Y":1,"IsDisabled":true,"EventActionName":"SaveEntityData","Style":{"width":84},"RowId":"2500000004","ColId":"2500000005","Id":"2500000006","IsNullable":true},{"Name":"BackToLast","Text":"返回","Type":"Button","ButtonType":"","X":3,"Y":1,"IsDisabled":true,"EventActionName":"BackToLast","Style":{"marginLeft":10},"RowId":"2500000007","ColId":"2500000008","Id":"2500000009","IsNullable":true}],"RowId":"2600000010","ColId":"2600000011","Id":"2600000012","IsNullable":true}],"X":1,"Y":1,"RowId":"2500000010","ColId":"2500000011","Id":"2500000012","IsNullable":true}]}